setup.cfg
setup.py
pom_weather/__init__.py
pom_weather/getweatherdata.py
pom_weather.egg-info/PKG-INFO
pom_weather.egg-info/SOURCES.txt
pom_weather.egg-info/dependency_links.txt
pom_weather.egg-info/not-zip-safe
pom_weather.egg-info/top_level.txt