Metadata-Version: 2.2
Name: pom_weather
Version: 0.0.0.2
Summary: https://github.com/AD1N23/pom_weather
Author-email: mpomykin@mail.ru
Dynamic: author-email
Dynamic: summary
